LICENSE
README.md
pyproject.toml
llmaudit/__init__.py
llmaudit/cli.py
llmaudit/report_template.html
llmaudit/scan_github_repos.py
llmaudit/sprawl.py
llmaudit.egg-info/PKG-INFO
llmaudit.egg-info/SOURCES.txt
llmaudit.egg-info/dependency_links.txt
llmaudit.egg-info/entry_points.txt
llmaudit.egg-info/requires.txt
llmaudit.egg-info/top_level.txt