Metadata-Version: 2.1
Name: llmaudit
Version: 0.1.3
Summary: A CLI tool to find LLM usage accross your repos
Author-email: PromptArmor <founders@promptarmor.com>
Project-URL: Company Page, https://promptarmor.com/
Project-URL: Homepage, https://github.com/promptarmor/llmaudit
Project-URL: Issues, https://github.com/promptarmor/llmaudit/issues
Classifier: Programming Language :: Python :: 3
Classifier: License :: OSI Approved :: Apache Software License
Classifier: Operating System :: OS Independent
Requires-Python: >=3.8
License-File: LICENSE
Requires-Dist: jinja2
Requires-Dist: codeowners
Requires-Dist: GitPython
Requires-Dist: PyGithub
